augmentations/__init__.py
augmentations/abstract.py
augmentations/basic.py
augmentations/rawinput.py
augmentations/tensor.py
callbacks/__init__.py
callbacks/basic.py
callbacks/swa.py
datasets/__init__.py
datasets/base.py
datasets/utils.py
lightning/__init__.py
lightning/base.py
loaders/__init__.py
loaders/abstract_loader.py
loaders/image_loaders.py
models/__init__.py
models/cumulative_probability_layer.py
models/pooling_layer.py
models/sybil.py
utils/__init__.py
utils/augmentations.py
utils/callbacks.py
utils/download.py
utils/loading.py
utils/registry.py
utils/sampler.py
vino-0.0.2.dist-info/LICENSE.txt
vino-0.0.2.dist-info/METADATA
vino-0.0.2.dist-info/WHEEL
vino-0.0.2.dist-info/entry_points.txt
vino-0.0.2.dist-info/top_level.txt
vino-0.0.2.dist-info/RECORD
